khello_world/__init__.py
khello_world/somecode.py
khello_world-0.0.1.dist-info/LICENSE
khello_world-0.0.1.dist-info/METADATA
khello_world-0.0.1.dist-info/WHEEL
khello_world-0.0.1.dist-info/top_level.txt
khello_world-0.0.1.dist-info/RECORD
